{
  "version": "6",
  "dialect": "sqlite",
  "id": "daf88112-4232-4da3-bea8-616d1889238b",
  "prevId": "00000000-0000-0000-0000-000000000000",
  "tables": {
    "logs": {
      "name": "logs",
      "columns": {
        "id": {
          "name": "id",
          "type": "integer",
          "primaryKey": true,
          "notNull": true,
          "autoincrement": true
        },
        "ts": {
          "name": "ts",
          "type": "integer",
          "primaryKey": false,
          "notNull": true,
          "autoincrement": false
        },
        "level": {
          "name": "level",
          "type": "text",
          "primaryKey": false,
          "notNull": true,
          "autoincrement": false
        },
        "source": {
          "name": "source",
          "type": "text",
          "primaryKey": false,
          "notNull": true,
          "autoincrement": false
        },
        "plugin_name": {
          "name": "plugin_name",
          "type": "text",
          "primaryKey": false,
          "notNull": false,
          "autoincrement": false
        },
        "message": {
          "name": "message",
          "type": "text",
          "primaryKey": false,
          "notNull": true,
          "autoincrement": false
        },
        "meta": {
          "name": "meta",
          "type": "text",
          "primaryKey": false,
          "notNull": false,
          "autoincrement": false
        },
        "error_name": {
          "name": "error_name",
          "type": "text",
          "primaryKey": false,
          "notNull": false,
          "autoincrement": false
        },
        "error_message": {
          "name": "error_message",
          "type": "text",
          "primaryKey": false,
          "notNull": false,
          "autoincrement": false
        },
        "error_stack": {
          "name": "error_stack",
          "type": "text",
          "primaryKey": false,
          "notNull": false,
          "autoincrement": false
        },
        "error_cause": {
          "name": "error_cause",
          "type": "text",
          "primaryKey": false,
          "notNull": false,
          "autoincrement": false
        }
      },
      "indexes": {
        "idx_logs_ts": {
          "name": "idx_logs_ts",
          "columns": [
            "ts"
          ],
          "isUnique": false
        },
        "idx_logs_level": {
          "name": "idx_logs_level",
          "columns": [
            "level"
          ],
          "isUnique": false
        },
        "idx_logs_source": {
          "name": "idx_logs_source",
          "columns": [
            "source"
          ],
          "isUnique": false
        },
        "idx_logs_plugin": {
          "name": "idx_logs_plugin",
          "columns": [
            "plugin_name"
          ],
          "isUnique": false
        },
        "idx_logs_ts_level": {
          "name": "idx_logs_ts_level",
          "columns": [
            "ts",
            "level"
          ],
          "isUnique": false
        },
        "idx_logs_ts_source": {
          "name": "idx_logs_ts_source",
          "columns": [
            "ts",
            "source"
          ],
          "isUnique": false
        }
      },
      "foreignKeys": {},
      "compositePrimaryKeys": {},
      "uniqueConstraints": {},
      "checkConstraints": {}
    }
  },
  "views": {},
  "enums": {},
  "_meta": {
    "schemas": {},
    "tables": {},
    "columns": {}
  },
  "internal": {
    "indexes": {}
  }
}